mailman_rest_event/__init__.py
mailman_rest_event/plugin.py
mailman_rest_event/handlers/__init__.py
mailman_rest_event/handlers/to_event.py
mailman_rest_event/pipelines/__init__.py
mailman_rest_event/pipelines/notify_pipeline.py
mailman_rest_event_tim-1.0.1.dist-info/LICENSE
mailman_rest_event_tim-1.0.1.dist-info/METADATA
mailman_rest_event_tim-1.0.1.dist-info/WHEEL
mailman_rest_event_tim-1.0.1.dist-info/top_level.txt
mailman_rest_event_tim-1.0.1.dist-info/RECORD
